Ejercicio 8/source/Decoder.v
module Decoder(in,enable,out);
    input [3:0] in;
    input enable;
    //what are the output ports and their sizes.
    output reg [7:0] out;
    //Whenever there is a change in the in, execute the always block.
    always @(in or enable) begin
        if (enable == 0)    
            case (in)   //case statement. Check all the 8 combinations.
                4'b0000 :  out <= 7'b0000001;
                4'b0001 :  out <= 7'b1001111;
                4'b0010 :  out <= 7'b0010010;
                4'b0011 :  out <= 7'b0000110;
                4'b0100 :  out <= 7'b1001100;
                4'b0101 :  out <= 7'b0100100;
                4'b0110 :  out <= 7'b0100000;
                4'b0111 :  out <= 7'b0001111;
                4'b1000 :  out <= 7'b0000000;
                4'b1001 :  out <= 7'b0000100;
                4'b1010 :  out <= 7'b0001000;
                4'b1011 :  out <= 7'b1100000;
                4'b1100 :  out <= 7'b0110001;
                4'b1101 :  out <= 7'b1000010;
                4'b1110 :  out <= 7'b0110000;
                4'b1111 :  out <= 7'b0111000;
                //To make sure that latches are not created create a default value for output.
                default :  out <= 7'b0000000; 
            endcase
    end
endmodule

Ejercicio 8/source/Countbcd.v
module Countbcd ( clk,enable, out);    // Declare 4-bit output port to get the counter values
    input clk,enable;
    output reg[3:0] out = 4'b0000;
  // This always block will be triggered at the rising edge of clk (0->1)
  // Once inside this block, it checks if the reset is 0, if yes then change out to zero
  // If reset is 1, then design should be allowed to count up, so increment counter
    always @ (posedge clk) begin
        if (enable == 1)
            if (out == 4'b1111)
                out <= 0;
            else if(out == 4'b1001)
                out <= 0;
            else 
                out <= out + 1;
    end
endmodule

Ejercicio 8/source/Comp.v
module Comp(a,b,out);
    input [4:0] a,b;
    wire [4:0] y;
    output out;
    xnor(y[4],a[4],b[4]);
    xnor(y[3],a[3],b[3]);
    xnor(y[2],a[2],b[2]);
    xnor(y[1],a[1],b[1]);
    xnor(y[0],a[0],b[0]);
    and(out,y[0],y[1],y[2],y[3],y[4]);
endmodule

Ejercicio 8/source/Countbit.v
module Countbit ( clk,rst, out);    // Declare 4-bit output port to get the counter values
    input clk,rst;
    output reg[4:0] out = 5'b00000;
  // This always block will be triggered at the rising edge of clk (0->1)
  // Once inside this block, it checks if the reset is 0, if yes then change out to zero
  // If reset is 1, then design should be allowed to count up, so increment counter
  always @ (posedge clk) begin
    if (out == 5'b11111)
        out <= 0;
    else if (rst==1)
        out <= 0;
    else 
        out <= out + 1;
  end
endmodule

Ejercicio 8/source/Gen_Clk.v
//Los skips aceptan hasta 1 decimal
`timescale 10us / 10us
module Gen_Clk(clk);
    parameter PERIOD=50;
    output reg clk;
    always
        begin: CLOCK_DRIVER
            clk <= 1'b0;
            #(PERIOD/2);
            clk <= 1'b1;
            #(PERIOD/2);
        end
endmodule

Ejercicio 8/source/Gen_Com.v
module Gen_Com(out);
    output out;
    assign out=1;
endmodule

Ejercicio 8/source/In.v
module In(out);
    output [4:0] out;
    assign out=5'b01001;
endmodule

Ejercicio 8/source/Gen_TritoCua.v
//Es la señal cuadrada formada a partir de la negación de la triangular

//Los skips aceptan hasta 1 decimal
`timescale 1ms / 100us
module Gen_TritoCua(clk);
    parameter PERIOD=50;
    output reg clk;
    always
        begin: CLOCK_DRIVER
            clk <= 1'b1;
            #(PERIOD/2);
            clk <= 1'b0;
            #(PERIOD/2);
        end
endmodule

Ejercicio 8/source/Main.v
//Defino tiempo de la simulacion
`timescale 100ms / 100ms
module main;
//Signal definitions
    wire Triang_cuad,Rst,Comparador,Cmp,Enable,Clk_2K,Enot;
    wire [4:0] ToComp, In;
    wire [3:0] BCDtoDisp_1, BCDtoDisp_2;
    wire [7:0] Out_1,Out_2;
    wire No1,No2,Anres;
//Calling function to generate signal
    Gen_TritoCua clkt_gen(Triang_cuad);
    In deffreq(In);
    Gen_Com ComRam(Cmp);
    Gen_Clk clk(Clk_2K);
//logica intermedia
    Countbit counter1(Triang_cuad,Rst, ToComp);
    Comp compara(In,ToComp,Comparador);
    and(Rst,1,Comparador);
    and(Enable,Cmp,Comparador);
    Countbcd count1(Clk_2K,Enable,BCDtoDisp_1);
    not(No1,BCDtoDisp_1[1]);
    not(No2,BCDtoDisp_1[2]);
    and(Anres,No1,No2,BCDtoDisp_1[0],BCDtoDisp_1[3]);
    Countbcd count2(Clk_2K,Anres,BCDtoDisp_2);
    not(Enot,Enable);
    Decoder dec1(BCDtoDisp_1,Enot,Out_1);
    Decoder dec2(BCDtoDisp_2,Enot,Out_2);
//Begin simulation
    initial begin
        #10
        $finish;
    end
//Seting path to get data for visualization of simulation
    reg dummy;
    reg[8*64:0] dumpfile_path = "output.vcd";
    initial begin
        dummy= $value$plusargs("VCD_PATH=%s", dumpfile_path);
        $dumpfile(dumpfile_path);
        $dumpvars(0,main);
    end
endmodule

Ejercicio 8/output.vcd
$date
	Fri Nov  1 00:26:06 2019
$end
$version
	Icarus Verilog
$end
$timescale
	10us
$end
$scope module main $end
$var wire 1 ! Anres $end
$var wire 1 " Cmp $end
$var wire 1 # Enable $end
$var wire 1 $ Enot $end
$var wire 5 % In [4:0] $end
$var wire 1 & No1 $end
$var wire 1 ' No2 $end
$var wire 1 ( Rst $end
$var wire 1 ) Triang_cuad $end
$var wire 5 * ToComp [4:0] $end
$var wire 8 + Out_2 [7:0] $end
$var wire 8 , Out_1 [7:0] $end
$var wire 1 - Comparador $end
$var wire 1 . Clk_2K $end
$var wire 4 / BCDtoDisp_2 [3:0] $end
$var wire 4 0 BCDtoDisp_1 [3:0] $end
$var reg 1 1 dummy $end
$var reg 513 2 dumpfile_path [512:0] $end
$scope module ComRam $end
$var wire 1 " out $end
$upscope $end
$scope module clk $end
$var reg 1 . clk $end
$scope begin CLOCK_DRIVER $end
$upscope $end
$upscope $end
$scope module clkt_gen $end
$var reg 1 ) clk $end
$scope begin CLOCK_DRIVER $end
$upscope $end
$upscope $end
$scope module compara $end
$var wire 5 3 a [4:0] $end
$var wire 1 - out $end
$var wire 5 4 y [4:0] $end
$var wire 5 5 b [4:0] $end
$upscope $end
$scope module count1 $end
$var wire 1 . clk $end
$var wire 1 # enable $end
$var reg 4 6 out [3:0] $end
$upscope $end
$scope module count2 $end
$var wire 1 . clk $end
$var wire 1 ! enable $end
$var reg 4 7 out [3:0] $end
$upscope $end
$scope module counter1 $end
$var wire 1 ) clk $end
$var wire 1 ( rst $end
$var reg 5 8 out [4:0] $end
$upscope $end
$scope module dec1 $end
$var wire 1 $ enable $end
$var wire 4 9 in [3:0] $end
$var reg 8 : out [7:0] $end
$upscope $end
$scope module dec2 $end
$var wire 1 $ enable $end
$var wire 4 ; in [3:0] $end
$var reg 8 < out [7:0] $end
$upscope $end
$scope module deffreq $end
$var wire 5 = out [4:0] $end
$upscope $end
$upscope $end
$enddefinitions $end
#0
$dumpvars
b1001 =
bx <
b0 ;
bx :
b0 9
b1 8
b0 7
b0 6
b1 5
b10111 4
b1001 3
b1101111011101010111010001110000011101010111010000101110011101100110001101100100 2
01
b0 0
b0 /
0.
0-
bx ,
bx +
b1 *
1)
0(
1'
1&
b1001 %
1$
0#
1"
0!
$end
#25
1.
#50
0.
#75
1.
#100
0.
#125
1.
#150
0.
#175
1.
#200
0.
#225
1.
#250
0.
#275
1.
#300
0.
#325
1.
#350
0.
#375
1.
#400
0.
#425
1.
#450
0.
#475
1.
#500
0.
#525
1.
#550
0.
#575
1.
#600
0.
#625
1.
#650
0.
#675
1.
#700
0.
#725
1.
#750
0.
#775
1.
#800
0.
#825
1.
#850
0.
#875
1.
#900
0.
#925
1.
#950
0.
#975
1.
#1000
0.
#1025
1.
#1050
0.
#1075
1.
#1100
0.
#1125
1.
#1150
0.
#1175
1.
#1200
0.
#1225
1.
#1250
0.
#1275
1.
#1300
0.
#1325
1.
#1350
0.
#1375
1.
#1400
0.
#1425
1.
#1450
0.
#1475
1.
#1500
0.
#1525
1.
#1550
0.
#1575
1.
#1600
0.
#1625
1.
#1650
0.
#1675
1.
#1700
0.
#1725
1.
#1750
0.
#1775
1.
#1800
0.
#1825
1.
#1850
0.
#1875
1.
#1900
0.
#1925
1.
#1950
0.
#1975
1.
#2000
0.
#2025
1.
#2050
0.
#2075
1.
#2100
0.
#2125
1.
#2150
0.
#2175
1.
#2200
0.
#2225
1.
#2250
0.
#2275
1.
#2300
0.
#2325
1.
#2350
0.
#2375
1.
#2400
0.
#2425
1.
#2450
0.
#2475
1.
#2500
0.
0)
#2525
1.
#2550
0.
#2575
1.
#2600
0.
#2625
1.
#2650
0.
#2675
1.
#2700
0.
#2725
1.
#2750
0.
#2775
1.
#2800
0.
#2825
1.
#2850
0.
#2875
1.
#2900
0.
#2925
1.
#2950
0.
#2975
1.
#3000
0.
#3025
1.
#3050
0.
#3075
1.
#3100
0.
#3125
1.
#3150
0.
#3175
1.
#3200
0.
#3225
1.
#3250
0.
#3275
1.
#3300
0.
#3325
1.
#3350
0.
#3375
1.
#3400
0.
#3425
1.
#3450
0.
#3475
1.
#3500
0.
#3525
1.
#3550
0.
#3575
1.
#3600
0.
#3625
1.
#3650
0.
#3675
1.
#3700
0.
#3725
1.
#3750
0.
#3775
1.
#3800
0.
#3825
1.
#3850
0.
#3875
1.
#3900
0.
#3925
1.
#3950
0.
#3975
1.
#4000
0.
#4025
1.
#4050
0.
#4075
1.
#4100
0.
#4125
1.
#4150
0.
#4175
1.
#4200
0.
#4225
1.
#4250
0.
#4275
1.
#4300
0.
#4325
1.
#4350
0.
#4375
1.
#4400
0.
#4425
1.
#4450
0.
#4475
1.
#4500
0.
#4525
1.
#4550
0.
#4575
1.
#4600
0.
#4625
1.
#4650
0.
#4675
1.
#4700
0.
#4725
1.
#4750
0.
#4775
1.
#4800
0.
#4825
1.
#4850
0.
#4875
1.
#4900
0.
#4925
1.
#4950
0.
#4975
1.
#5000
b10100 4
b10 *
b10 5
b10 8
0.
1)
#5025
1.
#5050
0.
#5075
1.
#5100
0.
#5125
1.
#5150
0.
#5175
1.
#5200
0.
#5225
1.
#5250
0.
#5275
1.
#5300
0.
#5325
1.
#5350
0.
#5375
1.
#5400
0.
#5425
1.
#5450
0.
#5475
1.
#5500
0.
#5525
1.
#5550
0.
#5575
1.
#5600
0.
#5625
1.
#5650
0.
#5675
1.
#5700
0.
#5725
1.
#5750
0.
#5775
1.
#5800
0.
#5825
1.
#5850
0.
#5875
1.
#5900
0.
#5925
1.
#5950
0.
#5975
1.
#6000
0.
#6025
1.
#6050
0.
#6075
1.
#6100
0.
#6125
1.
#6150
0.
#6175
1.
#6200
0.
#6225
1.
#6250
0.
#6275
1.
#6300
0.
#6325
1.
#6350
0.
#6375
1.
#6400
0.
#6425
1.
#6450
0.
#6475
1.
#6500
0.
#6525
1.
#6550
0.
#6575
1.
#6600
0.
#6625
1.
#6650
0.
#6675
1.
#6700
0.
#6725
1.
#6750
0.
#6775
1.
#6800
0.
#6825
1.
#6850
0.
#6875
1.
#6900
0.
#6925
1.
#6950
0.
#6975
1.
#7000
0.
#7025
1.
#7050
0.
#7075
1.
#7100
0.
#7125
1.
#7150
0.
#7175
1.
#7200
0.
#7225
1.
#7250
0.
#7275
1.
#7300
0.
#7325
1.
#7350
0.
#7375
1.
#7400
0.
#7425
1.
#7450
0.
#7475
1.
#7500
0.
0)
#7525
1.
#7550
0.
#7575
1.
#7600
0.
#7625
1.
#7650
0.
#7675
1.
#7700
0.
#7725
1.
#7750
0.
#7775
1.
#7800
0.
#7825
1.
#7850
0.
#7875
1.
#7900
0.
#7925
1.
#7950
0.
#7975
1.
#8000
0.
#8025
1.
#8050
0.
#8075
1.
#8100
0.
#8125
1.
#8150
0.
#8175
1.
#8200
0.
#8225
1.
#8250
0.
#8275
1.
#8300
0.
#8325
1.
#8350
0.
#8375
1.
#8400
0.
#8425
1.
#8450
0.
#8475
1.
#8500
0.
#8525
1.
#8550
0.
#8575
1.
#8600
0.
#8625
1.
#8650
0.
#8675
1.
#8700
0.
#8725
1.
#8750
0.
#8775
1.
#8800
0.
#8825
1.
#8850
0.
#8875
1.
#8900
0.
#8925
1.
#8950
0.
#8975
1.
#9000
0.
#9025
1.
#9050
0.
#9075
1.
#9100
0.
#9125
1.
#9150
0.
#9175
1.
#9200
0.
#9225
1.
#9250
0.
#9275
1.
#9300
0.
#9325
1.
#9350
0.
#9375
1.
#9400
0.
#9425
1.
#9450
0.
#9475
1.
#9500
0.
#9525
1.
#9550
0.
#9575
1.
#9600
0.
#9625
1.
#9650
0.
#9675
1.
#9700
0.
#9725
1.
#9750
0.
#9775
1.
#9800
0.
#9825
1.
#9850
0.
#9875
1.
#9900
0.
#9925
1.
#9950
0.
#9975
1.
#10000
b10101 4
b11 *
b11 5
b11 8
0.
1)
#10025
1.
#10050
0.
#10075
1.
#10100
0.
#10125
1.
#10150
0.
#10175
1.
#10200
0.
#10225
1.
#10250
0.
#10275
1.
#10300
0.
#10325
1.
#10350
0.
#10375
1.
#10400
0.
#10425
1.
#10450
0.
#10475
1.
#10500
0.
#10525
1.
#10550
0.
#10575
1.
#10600
0.
#10625
1.
#10650
0.
#10675
1.
#10700
0.
#10725
1.
#10750
0.
#10775
1.
#10800
0.
#10825
1.
#10850
0.
#10875
1.
#10900
0.
#10925
1.
#10950
0.
#10975
1.
#11000
0.
#11025
1.
#11050
0.
#11075
1.
#11100
0.
#11125
1.
#11150
0.
#11175
1.
#11200
0.
#11225
1.
#11250
0.
#11275
1.
#11300
0.
#11325
1.
#11350
0.
#11375
1.
#11400
0.
#11425
1.
#11450
0.
#11475
1.
#11500
0.
#11525
1.
#11550
0.
#11575
1.
#11600
0.
#11625
1.
#11650
0.
#11675
1.
#11700
0.
#11725
1.
#11750
0.
#11775
1.
#11800
0.
#11825
1.
#11850
0.
#11875
1.
#11900
0.
#11925
1.
#11950
0.
#11975
1.
#12000
0.
#12025
1.
#12050
0.
#12075
1.
#12100
0.
#12125
1.
#12150
0.
#12175
1.
#12200
0.
#12225
1.
#12250
0.
#12275
1.
#12300
0.
#12325
1.
#12350
0.
#12375
1.
#12400
0.
#12425
1.
#12450
0.
#12475
1.
#12500
0.
0)
#12525
1.
#12550
0.
#12575
1.
#12600
0.
#12625
1.
#12650
0.
#12675
1.
#12700
0.
#12725
1.
#12750
0.
#12775
1.
#12800
0.
#12825
1.
#12850
0.
#12875
1.
#12900
0.
#12925
1.
#12950
0.
#12975
1.
#13000
0.
#13025
1.
#13050
0.
#13075
1.
#13100
0.
#13125
1.
#13150
0.
#13175
1.
#13200
0.
#13225
1.
#13250
0.
#13275
1.
#13300
0.
#13325
1.
#13350
0.
#13375
1.
#13400
0.
#13425
1.
#13450
0.
#13475
1.
#13500
0.
#13525
1.
#13550
0.
#13575
1.
#13600
0.
#13625
1.
#13650
0.
#13675
1.
#13700
0.
#13725
1.
#13750
0.
#13775
1.
#13800
0.
#13825
1.
#13850
0.
#13875
1.
#13900
0.
#13925
1.
#13950
0.
#13975
1.
#14000
0.
#14025
1.
#14050
0.
#14075
1.
#14100
0.
#14125
1.
#14150
0.
#14175
1.
#14200
0.
#14225
1.
#14250
0.
#14275
1.
#14300
0.
#14325
1.
#14350
0.
#14375
1.
#14400
0.
#14425
1.
#14450
0.
#14475
1.
#14500
0.
#14525
1.
#14550
0.
#14575
1.
#14600
0.
#14625
1.
#14650
0.
#14675
1.
#14700
0.
#14725
1.
#14750
0.
#14775
1.
#14800
0.
#14825
1.
#14850
0.
#14875
1.
#14900
0.
#14925
1.
#14950
0.
#14975
1.
#15000
b10010 4
b100 *
b100 5
b100 8
0.
1)
#15025
1.
#15050
0.
#15075
1.
#15100
0.
#15125
1.
#15150
0.
#15175
1.
#15200
0.
#15225
1.
#15250
0.
#15275
1.
#15300
0.
#15325
1.
#15350
0.
#15375
1.
#15400
0.
#15425
1.
#15450
0.
#15475
1.
#15500
0.
#15525
1.
#15550
0.
#15575
1.
#15600
0.
#15625
1.
#15650
0.
#15675
1.
#15700
0.
#15725
1.
#15750
0.
#15775
1.
#15800
0.
#15825
1.
#15850
0.
#15875
1.
#15900
0.
#15925
1.
#15950
0.
#15975
1.
#16000
0.
#16025
1.
#16050
0.
#16075
1.
#16100
0.
#16125
1.
#16150
0.
#16175
1.
#16200
0.
#16225
1.
#16250
0.
#16275
1.
#16300
0.
#16325
1.
#16350
0.
#16375
1.
#16400
0.
#16425
1.
#16450
0.
#16475
1.
#16500
0.
#16525
1.
#16550
0.
#16575
1.
#16600
0.
#16625
1.
#16650
0.
#16675
1.
#16700
0.
#16725
1.
#16750
0.
#16775
1.
#16800
0.
#16825
1.
#16850
0.
#16875
1.
#16900
0.
#16925
1.
#16950
0.
#16975
1.
#17000
0.
#17025
1.
#17050
0.
#17075
1.
#17100
0.
#17125
1.
#17150
0.
#17175
1.
#17200
0.
#17225
1.
#17250
0.
#17275
1.
#17300
0.
#17325
1.
#17350
0.
#17375
1.
#17400
0.
#17425
1.
#17450
0.
#17475
1.
#17500
0.
0)
#17525
1.
#17550
0.
#17575
1.
#17600
0.
#17625
1.
#17650
0.
#17675
1.
#17700
0.
#17725
1.
#17750
0.
#17775
1.
#17800
0.
#17825
1.
#17850
0.
#17875
1.
#17900
0.
#17925
1.
#17950
0.
#17975
1.
#18000
0.
#18025
1.
#18050
0.
#18075
1.
#18100
0.
#18125
1.
#18150
0.
#18175
1.
#18200
0.
#18225
1.
#18250
0.
#18275
1.
#18300
0.
#18325
1.
#18350
0.
#18375
1.
#18400
0.
#18425
1.
#18450
0.
#18475
1.
#18500
0.
#18525
1.
#18550
0.
#18575
1.
#18600
0.
#18625
1.
#18650
0.
#18675
1.
#18700
0.
#18725
1.
#18750
0.
#18775
1.
#18800
0.
#18825
1.
#18850
0.
#18875
1.
#18900
0.
#18925
1.
#18950
0.
#18975
1.
#19000
0.
#19025
1.
#19050
0.
#19075
1.
#19100
0.
#19125
1.
#19150
0.
#19175
1.
#19200
0.
#19225
1.
#19250
0.
#19275
1.
#19300
0.
#19325
1.
#19350
0.
#19375
1.
#19400
0.
#19425
1.
#19450
0.
#19475
1.
#19500
0.
#19525
1.
#19550
0.
#19575
1.
#19600
0.
#19625
1.
#19650
0.
#19675
1.
#19700
0.
#19725
1.
#19750
0.
#19775
1.
#19800
0.
#19825
1.
#19850
0.
#19875
1.
#19900
0.
#19925
1.
#19950
0.
#19975
1.
#20000
b10011 4
b101 *
b101 5
b101 8
0.
1)
#20025
1.
#20050
0.
#20075
1.
#20100
0.
#20125
1.
#20150
0.
#20175
1.
#20200
0.
#20225
1.
#20250
0.
#20275
1.
#20300
0.
#20325
1.
#20350
0.
#20375
1.
#20400
0.
#20425
1.
#20450
0.
#20475
1.
#20500
0.
#20525
1.
#20550
0.
#20575
1.
#20600
0.
#20625
1.
#20650
0.
#20675
1.
#20700
0.
#20725
1.
#20750
0.
#20775
1.
#20800
0.
#20825
1.
#20850
0.
#20875
1.
#20900
0.
#20925
1.
#20950
0.
#20975
1.
#21000
0.
#21025
1.
#21050
0.
#21075
1.
#21100
0.
#21125
1.
#21150
0.
#21175
1.
#21200
0.
#21225
1.
#21250
0.
#21275
1.
#21300
0.
#21325
1.
#21350
0.
#21375
1.
#21400
0.
#21425
1.
#21450
0.
#21475
1.
#21500
0.
#21525
1.
#21550
0.
#21575
1.
#21600
0.
#21625
1.
#21650
0.
#21675
1.
#21700
0.
#21725
1.
#21750
0.
#21775
1.
#21800
0.
#21825
1.
#21850
0.
#21875
1.
#21900
0.
#21925
1.
#21950
0.
#21975
1.
#22000
0.
#22025
1.
#22050
0.
#22075
1.
#22100
0.
#22125
1.
#22150
0.
#22175
1.
#22200
0.
#22225
1.
#22250
0.
#22275
1.
#22300
0.
#22325
1.
#22350
0.
#22375
1.
#22400
0.
#22425
1.
#22450
0.
#22475
1.
#22500
0.
0)
#22525
1.
#22550
0.
#22575
1.
#22600
0.
#22625
1.
#22650
0.
#22675
1.
#22700
0.
#22725
1.
#22750
0.
#22775
1.
#22800
0.
#22825
1.
#22850
0.
#22875
1.
#22900
0.
#22925
1.
#22950
0.
#22975
1.
#23000
0.
#23025
1.
#23050
0.
#23075
1.
#23100
0.
#23125
1.
#23150
0.
#23175
1.
#23200
0.
#23225
1.
#23250
0.
#23275
1.
#23300
0.
#23325
1.
#23350
0.
#23375
1.
#23400
0.
#23425
1.
#23450
0.
#23475
1.
#23500
0.
#23525
1.
#23550
0.
#23575
1.
#23600
0.
#23625
1.
#23650
0.
#23675
1.
#23700
0.
#23725
1.
#23750
0.
#23775
1.
#23800
0.
#23825
1.
#23850
0.
#23875
1.
#23900
0.
#23925
1.
#23950
0.
#23975
1.
#24000
0.
#24025
1.
#24050
0.
#24075
1.
#24100
0.
#24125
1.
#24150
0.
#24175
1.
#24200
0.
#24225
1.
#24250
0.
#24275
1.
#24300
0.
#24325
1.
#24350
0.
#24375
1.
#24400
0.
#24425
1.
#24450
0.
#24475
1.
#24500
0.
#24525
1.
#24550
0.
#24575
1.
#24600
0.
#24625
1.
#24650
0.
#24675
1.
#24700
0.
#24725
1.
#24750
0.
#24775
1.
#24800
0.
#24825
1.
#24850
0.
#24875
1.
#24900
0.
#24925
1.
#24950
0.
#24975
1.
#25000
b10000 4
b110 *
b110 5
b110 8
0.
1)
#25025
1.
#25050
0.
#25075
1.
#25100
0.
#25125
1.
#25150
0.
#25175
1.
#25200
0.
#25225
1.
#25250
0.
#25275
1.
#25300
0.
#25325
1.
#25350
0.
#25375
1.
#25400
0.
#25425
1.
#25450
0.
#25475
1.
#25500
0.
#25525
1.
#25550
0.
#25575
1.
#25600
0.
#25625
1.
#25650
0.
#25675
1.
#25700
0.
#25725
1.
#25750
0.
#25775
1.
#25800
0.
#25825
1.
#25850
0.
#25875
1.
#25900
0.
#25925
1.
#25950
0.
#25975
1.
#26000
0.
#26025
1.
#26050
0.
#26075
1.
#26100
0.
#26125
1.
#26150
0.
#26175
1.
#26200
0.
#26225
1.
#26250
0.
#26275
1.
#26300
0.
#26325
1.
#26350
0.
#26375
1.
#26400
0.
#26425
1.
#26450
0.
#26475
1.
#26500
0.
#26525
1.
#26550
0.
#26575
1.
#26600
0.
#26625
1.
#26650
0.
#26675
1.
#26700
0.
#26725
1.
#26750
0.
#26775
1.
#26800
0.
#26825
1.
#26850
0.
#26875
1.
#26900
0.
#26925
1.
#26950
0.
#26975
1.
#27000
0.
#27025
1.
#27050
0.
#27075
1.
#27100
0.
#27125
1.
#27150
0.
#27175
1.
#27200
0.
#27225
1.
#27250
0.
#27275
1.
#27300
0.
#27325
1.
#27350
0.
#27375
1.
#27400
0.
#27425
1.
#27450
0.
#27475
1.
#27500
0.
0)
#27525
1.
#27550
0.
#27575
1.
#27600
0.
#27625
1.
#27650
0.
#27675
1.
#27700
0.
#27725
1.
#27750
0.
#27775
1.
#27800
0.
#27825
1.
#27850
0.
#27875
1.
#27900
0.
#27925
1.
#27950
0.
#27975
1.
#28000
0.
#28025
1.
#28050
0.
#28075
1.
#28100
0.
#28125
1.
#28150
0.
#28175
1.
#28200
0.
#28225
1.
#28250
0.
#28275
1.
#28300
0.
#28325
1.
#28350
0.
#28375
1.
#28400
0.
#28425
1.
#28450
0.
#28475
1.
#28500
0.
#28525
1.
#28550
0.
#28575
1.
#28600
0.
#28625
1.
#28650
0.
#28675
1.
#28700
0.
#28725
1.
#28750
0.
#28775
1.
#28800
0.
#28825
1.
#28850
0.
#28875
1.
#28900
0.
#28925
1.
#28950
0.
#28975
1.
#29000
0.
#29025
1.
#29050
0.
#29075
1.
#29100
0.
#29125
1.
#29150
0.
#29175
1.
#29200
0.
#29225
1.
#29250
0.
#29275
1.
#29300
0.
#29325
1.
#29350
0.
#29375
1.
#29400
0.
#29425
1.
#29450
0.
#29475
1.
#29500
0.
#29525
1.
#29550
0.
#29575
1.
#29600
0.
#29625
1.
#29650
0.
#29675
1.
#29700
0.
#29725
1.
#29750
0.
#29775
1.
#29800
0.
#29825
1.
#29850
0.
#29875
1.
#29900
0.
#29925
1.
#29950
0.
#29975
1.
#30000
b10001 4
b111 *
b111 5
b111 8
0.
1)
#30025
1.
#30050
0.
#30075
1.
#30100
0.
#30125
1.
#30150
0.
#30175
1.
#30200
0.
#30225
1.
#30250
0.
#30275
1.
#30300
0.
#30325
1.
#30350
0.
#30375
1.
#30400
0.
#30425
1.
#30450
0.
#30475
1.
#30500
0.
#30525
1.
#30550
0.
#30575
1.
#30600
0.
#30625
1.
#30650
0.
#30675
1.
#30700
0.
#30725
1.
#30750
0.
#30775
1.
#30800
0.
#30825
1.
#30850
0.
#30875
1.
#30900
0.
#30925
1.
#30950
0.
#30975
1.
#31000
0.
#31025
1.
#31050
0.
#31075
1.
#31100
0.
#31125
1.
#31150
0.
#31175
1.
#31200
0.
#31225
1.
#31250
0.
#31275
1.
#31300
0.
#31325
1.
#31350
0.
#31375
1.
#31400
0.
#31425
1.
#31450
0.
#31475
1.
#31500
0.
#31525
1.
#31550
0.
#31575
1.
#31600
0.
#31625
1.
#31650
0.
#31675
1.
#31700
0.
#31725
1.
#31750
0.
#31775
1.
#31800
0.
#31825
1.
#31850
0.
#31875
1.
#31900
0.
#31925
1.
#31950
0.
#31975
1.
#32000
0.
#32025
1.
#32050
0.
#32075
1.
#32100
0.
#32125
1.
#32150
0.
#32175
1.
#32200
0.
#32225
1.
#32250
0.
#32275
1.
#32300
0.
#32325
1.
#32350
0.
#32375
1.
#32400
0.
#32425
1.
#32450
0.
#32475
1.
#32500
0.
0)
#32525
1.
#32550
0.
#32575
1.
#32600
0.
#32625
1.
#32650
0.
#32675
1.
#32700
0.
#32725
1.
#32750
0.
#32775
1.
#32800
0.
#32825
1.
#32850
0.
#32875
1.
#32900
0.
#32925
1.
#32950
0.
#32975
1.
#33000
0.
#33025
1.
#33050
0.
#33075
1.
#33100
0.
#33125
1.
#33150
0.
#33175
1.
#33200
0.
#33225
1.
#33250
0.
#33275
1.
#33300
0.
#33325
1.
#33350
0.
#33375
1.
#33400
0.
#33425
1.
#33450
0.
#33475
1.
#33500
0.
#33525
1.
#33550
0.
#33575
1.
#33600
0.
#33625
1.
#33650
0.
#33675
1.
#33700
0.
#33725
1.
#33750
0.
#33775
1.
#33800
0.
#33825
1.
#33850
0.
#33875
1.
#33900
0.
#33925
1.
#33950
0.
#33975
1.
#34000
0.
#34025
1.
#34050
0.
#34075
1.
#34100
0.
#34125
1.
#34150
0.
#34175
1.
#34200
0.
#34225
1.
#34250
0.
#34275
1.
#34300
0.
#34325
1.
#34350
0.
#34375
1.
#34400
0.
#34425
1.
#34450
0.
#34475
1.
#34500
0.
#34525
1.
#34550
0.
#34575
1.
#34600
0.
#34625
1.
#34650
0.
#34675
1.
#34700
0.
#34725
1.
#34750
0.
#34775
1.
#34800
0.
#34825
1.
#34850
0.
#34875
1.
#34900
0.
#34925
1.
#34950
0.
#34975
1.
#35000
b11110 4
b1000 *
b1000 5
b1000 8
0.
1)
